geopop/__init__.py
geopop/common.py
geopop/foliummap.py
geopop/geopop.py
geopop/ipyleafletmap.py
geopop-0.0.3.dist-info/licenses/LICENSE
geopop-0.0.3.dist-info/METADATA
geopop-0.0.3.dist-info/WHEEL
geopop-0.0.3.dist-info/entry_points.txt
geopop-0.0.3.dist-info/top_level.txt
geopop-0.0.3.dist-info/RECORD
